upwork_analysis/__init__.py
upwork_analysis/analyze_data.py
upwork_analysis/data_analysis.ipynb
upwork_analysis/py.typed
upwork_analysis/scrape_data.py
upwork_analysis-1.0.0.dist-info/LICENSE
upwork_analysis-1.0.0.dist-info/METADATA
upwork_analysis-1.0.0.dist-info/WHEEL
upwork_analysis-1.0.0.dist-info/entry_points.txt
upwork_analysis-1.0.0.dist-info/top_level.txt
upwork_analysis-1.0.0.dist-info/RECORD
