Metadata-Version: 2.1
Name: upwork_analysis
Version: 1.0.0
Summary: A Python package that scrapes and analyzes Upwork job listings.
Author-email: Yazan Sharaya <yazan.sharaya.yes@gmail.com>
License: MIT License
Project-URL: Repostiroy, https://github.com/Yazan-Sharaya/upwork_analysis
Keywords: scraping,undetected,selenium,crawling,automation,data analysis
Classifier: Environment :: Console
Classifier: Framework :: Jupyter
Classifier: Intended Audience :: Developers
Classifier: License :: OSI Approved :: MIT License
Classifier: Operating System :: OS Independent
Classifier: Programming Language :: Python :: 3.7
Classifier: Programming Language :: Python :: 3.8
Classifier: Programming Language :: Python :: 3.9
Classifier: Programming Language :: Python :: 3.10
Classifier: Programming Language :: Python :: 3.11
Classifier: Programming Language :: Python :: 3.12
Classifier: Programming Language :: Python :: 3.13
Classifier: Topic :: Scientific/Engineering :: Information Analysis
Classifier: Topic :: Scientific/Engineering :: Visualization
Classifier: Typing :: Typed
Requires-Python: >=3.7
License-File: LICENSE
Requires-Dist: seleniumbase
Requires-Dist: beautifulsoup4
Requires-Dist: scikit-learn
Requires-Dist: pandas
Requires-Dist: scipy
Requires-Dist: seaborn
